odoo/addons/shopinvader_product_media/README.rst
odoo/addons/shopinvader_product_media/__init__.py
odoo/addons/shopinvader_product_media/__manifest__.py
odoo/addons/shopinvader_product_media/data/ir_product_export.xml
odoo13_addon_shopinvader_product_media-13.0.1.0.1.dist-info/METADATA
odoo13_addon_shopinvader_product_media-13.0.1.0.1.dist-info/WHEEL
odoo13_addon_shopinvader_product_media-13.0.1.0.1.dist-info/top_level.txt
odoo13_addon_shopinvader_product_media-13.0.1.0.1.dist-info/RECORD
